access_guard/__init__.py
access_guard/final.py
access_guard/py.typed
access_guard-0.1.6.dist-info/licenses/LICENSE
access_guard-0.1.6.dist-info/METADATA
access_guard-0.1.6.dist-info/WHEEL
access_guard-0.1.6.dist-info/top_level.txt
access_guard-0.1.6.dist-info/RECORD
